{
    "lastmod": "2025-7-3",
    "page_url": "",
    "page_title": "Touchiroa zeylanica",
    "plant_slug": "touchiroa-zeylanica",
    "plant_name_scientific": "touchiroa zeylanica",
    "intro": "Touchiroa zeylanica, commonly known as the Ceylon touchwood, is a flowering plant native to the tropical regions of South and Southeast Asia. It belongs to the family Meliaceae, which includes mahogany and other tropical hardwoods. The plant is characterized by its smooth, dark-brown bark and compound leaves with opposite arrangement. Its flowers are small and greenish-yellow, typically appearing in clusters, and it produces small, round fruits containing a single seed. The tree is valued for its durable wood, which is used in construction and furniture-making."
}
