{
    "lastmod": "2025-7-4",
    "page_url": "",
    "page_title": "Tristemma albiflorum",
    "plant_slug": "tristemma-albiflorum",
    "plant_name_scientific": "tristemma albiflorum",
    "intro": "Tristemma albiflorum, commonly known as the white-flowered tristemma, is a flowering plant native to parts of Southeast Asia. It belongs to the family Rubiaceae, which includes over 13,000 species of flowering plants. The plant is characterized by its small, white flowers that bloom in clusters, often in the spring or early summer. Its leaves are typically opposite and elliptical, with a smooth or slightly hairy surface. Tristemma albiflorum is often found in moist, shaded environments such as forest understories or along streambanks."
}
