{
    "lastmod": "2025-6-14",
    "page_url": "",
    "page_title": "Clavija brachystachys",
    "plant_slug": "clavija-brachystachys",
    "plant_name_scientific": "clavija brachystachys",
    "intro": "Clavija brachystachys, commonly known as the short-stemmed clavija, is a flowering plant native to the Andes region of South America. It belongs to the family Polygonaceae, which includes plants known for their distinctive leaf shapes and often edible roots. The plant is characterized by its upright, branching stems and clusters of small, greenish-white flowers that appear in late summer. Its leaves are typically lance-shaped and covered in a dense layer of fine hairs. Clavija brachystachys is valued for its ornamental appeal and has been studied for its potential medicinal properties."
}
