{
    "lastmod": "2025-6-23",
    "page_url": "",
    "page_title": "Macrolobium conjunctum",
    "plant_slug": "macrolobium-conjunctum",
    "plant_name_scientific": "macrolobium conjunctum",
    "intro": "Macrolobium conjunctum, commonly known as the clustered macrolobium, is a tropical shrub native to Central and South America. It belongs to the family Malvaceae, which includes hibiscus and cotton plants. The plant is characterized by its large, lobed leaves that are often hairy and have a rough texture. Its flowers are typically yellow or orange and are clustered in inflorescences, adding to its ornamental value. The plant is often grown for its attractive foliage and is used in horticulture for its aesthetic appeal."
}
