{
    "lastmod": "2025-6-22",
    "page_url": "",
    "page_title": "Laoberdes",
    "plant_slug": "laoberdes",
    "plant_name_scientific": "laoberdes",
    "intro": "Laoberdes, commonly known as the ghost orchid, is a rare and enigmatic plant native to the southeastern United States. It is an epiphytic orchid, meaning it grows on the surface of trees without deriving nutrients from them. The plant has a unique structure with a single, slender stem and a single, waxy leaf that is often covered in a fine, white coating. Its flowers are small, white, and emit a faint, sweet scent, which attracts specific pollinators. Due to its habitat requirements and limited distribution, Laoberdes is considered a vulnerable species."
}
