{
    "lastmod": "2025-6-22",
    "page_url": "",
    "page_title": "Lemaireocereus longispinus",
    "plant_slug": "lemaireocereus-longispinus",
    "plant_name_scientific": "lemaireocereus longispinus",
    "intro": "Lemaireocereus longispinus, commonly known as the long-spined cactus, is a species native to the Canary Islands. It is a columnar cactus characterized by its tall, cylindrical stems and long, sharp spines. The plant typically grows in rocky or coastal areas, where it thrives in well-drained soil and full sun. Its flowers are usually yellow or orange, appearing in late spring or early summer. Lemaireocereus longispinus is often cultivated for its striking appearance and drought tolerance."
}
