{
    "lastmod": "2025-6-7",
    "page_url": "",
    "page_title": "Acinodendron tuerckheimii",
    "plant_slug": "acinodendron-tuerckheimii",
    "plant_name_scientific": "acinodendron tuerckheimii",
    "intro": "Acinodendron tuerckheimii, commonly known as the Tuerckheim's acinodendron, is a rare and endemic plant species native to Madagascar. It belongs to the family Rubiaceae and is characterized by its small, clustered flowers and woody stems. The plant typically grows in shaded, humid environments within the island's tropical forests. Its leaves are elliptical and often have a slightly serrated edge, while its flowers are white or pale pink. Due to its restricted habitat and threats from deforestation, it is considered vulnerable to extinction.",
    "distribution_native": [],
    "distribution_introduced": []
}
