{
    "lastmod": "2025-6-19",
    "page_url": "",
    "page_title": "Gumira bracteata",
    "plant_slug": "gumira-bracteata",
    "plant_name_scientific": "gumira bracteata",
    "intro": "Gumira bracteata, commonly known as the bracted gumira, is a flowering plant native to parts of Southeast Asia. It belongs to the family Rubiaceae, which includes many ornamental and economically important species. The plant is characterized by its small, clustered flowers that are typically white or pale yellow in color. Its leaves are opposite and often have a glossy appearance, contributing to its ornamental value. Gumira bracteata is often cultivated for its aesthetic appeal in gardens and as a decorative plant."
}
