{
    "lastmod": "2025-6-20",
    "page_url": "",
    "page_title": "Heliotropium microspermum",
    "plant_slug": "heliotropium-microspermum",
    "plant_name_scientific": "heliotropium microspermum",
    "intro": "Heliotropium microspermum, commonly known as the small-seeded heliotrope, is a flowering plant native to tropical and subtropical regions. It belongs to the family Malvaceae, which includes other plants like cotton and hibiscus. The plant is characterized by its small, showy flowers that typically bloom in shades of purple or pink. Its leaves are usually ovate or elliptical, with a smooth or slightly hairy surface. Heliotropium microspermum is often found in disturbed soils and can thrive in coastal areas due to its tolerance for saline conditions."
}
