{
    "lastmod": "2025-6-30",
    "page_url": "",
    "page_title": "Roupala javanica",
    "plant_slug": "roupala-javanica",
    "plant_name_scientific": "roupala javanica",
    "intro": "Roupala javanica, commonly known as the Javan roupala, is a deciduous tree native to Southeast Asia. It belongs to the family Achariaceae and is characterized by its smooth, grayish bark and alternate, simple leaves. The plant produces small, yellowish flowers that are clustered in panicles, followed by oval, woody fruits containing single seeds. Roupala javanica is often found in lowland forests and is valued for its timber and ornamental qualities. Its botanical features make it an important species in the study of tropical flora."
}
