{
    "lastmod": "2025-6-17",
    "page_url": "",
    "page_title": "Echium briquetii",
    "plant_slug": "echium-briquetii",
    "plant_name_scientific": "echium briquetii",
    "intro": "Echium briquetii, commonly known as the Canary Island thistle, is a flowering plant native to the Canary Islands. It is a member of the Boraginaceae family and is characterized by its striking blue or purple flowers. The plant typically grows in rocky or coastal habitats, showcasing its adaptability to harsh environments. Its leaves are generally hairy and lance-shaped, while its stems are often spiny. Echium briquetii is valued for its ornamental appeal and ecological importance in supporting local pollinators."
}
