{
    "lastmod": "2025-6-18",
    "page_url": "",
    "page_title": "Erblichia standleyi",
    "plant_slug": "erblichia-standleyi",
    "plant_name_scientific": "erblichia standleyi",
    "intro": "Erblichia standleyi, commonly known as the Standley's erblichia, is a species of flowering plant native to Mexico. It belongs to the family Malvaceae, which includes hibiscus and cotton. The plant is characterized by its showy, trumpet-shaped flowers that are typically pink or purple in color. It thrives in tropical and subtropical climates, often growing in moist, well-drained soils. Due to its ornamental value, it is occasionally cultivated in gardens and botanical collections."
}
