{
    "lastmod": "2025-7-2",
    "page_url": "",
    "page_title": "Steganthus",
    "plant_slug": "steganthus",
    "plant_name_scientific": "steganthus",
    "intro": "Steganthus, commonly known as the \"hidden flower,\" is a genus of flowering plants in the family Aizoaceae. These plants are native to southern Africa, particularly South Africa, and are known for their unique, often intricate flower structures. Steganthus species typically have small, star-shaped flowers that are often brightly colored, with petals that are tightly packed together. They are adapted to arid environments and are often found growing in rocky or sandy soils. The genus includes several species, some of which are cultivated for their ornamental value in gardens."
}
