{
    "lastmod": "2025-6-13",
    "page_url": "",
    "page_title": "Browningia utcubambensis",
    "plant_slug": "browningia-utcubambensis",
    "plant_name_scientific": "browningia utcubambensis",
    "intro": "Browningia utcubambensis, commonly known as the Ecuadorian bellflower, is a flowering plant native to the Andean regions of Ecuador. It belongs to the Campanulaceae family and is characterized by its bell-shaped, blue or violet flowers. The plant typically grows in moist, shaded environments at high altitudes. Its leaves are broad and lanceolate, with a rough texture. Browningia utcubambensis is valued for its ornamental appeal and is often cultivated in gardens for its striking floral display."
}
